gpt2_client/__init__.py
gpt2_client/encoder.py
gpt2_client/gpt2_client.py
gpt2_client/model.py
gpt2_client/sample.py
gpt2_client-2.0.dist-info/LICENSE.txt
gpt2_client-2.0.dist-info/METADATA
gpt2_client-2.0.dist-info/WHEEL
gpt2_client-2.0.dist-info/top_level.txt
gpt2_client-2.0.dist-info/RECORD
