Metadata-Version: 2.1
Name: gpt2-client
Version: 2.0
Summary: Easy-to-use Wrapper for the GPT-2 117M, 345M, and 774M Transformer Models
Home-page: https://github.com/rish-16/gpt2client
Author: Rishabh Anand
Author-email: mail.rishabh.anand@gmail.com
License: MIT
Download-URL: https://github.com/rish-16/gpt2client/archive/2.0.tar.gz
Keywords: gpt-2,AI,ML,wrapper,transformer,machine learning,openai,text generation
Platform: UNKNOWN
Classifier: Development Status :: 4 - Beta
Classifier: Intended Audience :: Developers
Classifier: Topic :: Software Development :: Build Tools
Classifier: License :: OSI Approved :: MIT License
Classifier: Programming Language :: Python :: 3
Classifier: Programming Language :: Python :: 3.4
Classifier: Programming Language :: Python :: 3.5
Classifier: Programming Language :: Python :: 3.6
Requires-Dist: numpy
Requires-Dist: tensorflow
Requires-Dist: regex
Requires-Dist: tqdm
Requires-Dist: requests
Requires-Dist: termcolor
Requires-Dist: gpt-2-simple
